{
  "active": false,
  "connections": {
    "Schedule Trigger": {
      "main": [
        [
          {
            "node": "n8n",
            "type": "main",
            "index": 0
          }
        ]
      ]
    }
  },
  "createdAt": "2025-06-04T12:43:26.551Z",
  "id": "nV6rcOMxZbav7T3h",
  "isArchived": true,
  "meta": null,
  "name": "My workflow 9",
  "nodes": [
    {
      "parameters": {
        "rule": {
          "interval": [
            {}
          ]
        }
      },
      "type": "n8n-nodes-base.scheduleTrigger",
      "typeVersion": 1.2,
      "position": [
        0,
        0
      ],
      "id": "eb1e1bfb-9b9b-4e3c-bd14-4d4474a670ea",
      "name": "Schedule Trigger"
    },
    {
      "parameters": {
        "filters": {},
        "requestOptions": {}
      },
      "type": "n8n-nodes-base.n8n",
      "typeVersion": 1,
      "position": [
        220,
        0
      ],
      "id": "0333ba7f-82fb-480c-a9b8-8aa82eb02eb1",
      "name": "n8n"
    }
  ],
  "pinData": {},
  "settings": {
    "executionOrder": "v1"
  },
  "staticData": null,
  "tags": [],
  "triggerCount": 0,
  "updatedAt": "2025-06-04T12:46:05.000Z",
  "versionId": "5a98edba-c72a-4589-989b-5bd95d71da50"
}